mercari/__init__.py
mercari/common.py
mercari/mercari.py
mercari/rakuma.py
mercari_python-0.4.dist-info/METADATA
mercari_python-0.4.dist-info/WHEEL
mercari_python-0.4.dist-info/top_level.txt
mercari_python-0.4.dist-info/RECORD
