Metadata-Version: 2.1
Name: mercari-python
Version: 0.4
Summary: UNKNOWN
Home-page: UNKNOWN
Author: Philippe Remy
Author-email: UNKNOWN
License: UNKNOWN
Platform: UNKNOWN
Requires-Dist: mailthon
Requires-Dist: requests
Requires-Dist: beautifulsoup4
Requires-Dist: lxml
Requires-Dist: wget
